MANIFEST.in
README.md
setup.py
ast_boiler_core/.env.default
ast_boiler_core/__init__.py
ast_boiler_core/command.py
ast_boiler_core/config.py
ast_boiler_core.egg-info/PKG-INFO
ast_boiler_core.egg-info/SOURCES.txt
ast_boiler_core.egg-info/dependency_links.txt
ast_boiler_core.egg-info/entry_points.txt
ast_boiler_core.egg-info/not-zip-safe
ast_boiler_core.egg-info/requires.txt
ast_boiler_core.egg-info/top_level.txt
src/__init__.py