Metadata-Version: 2.1
Name: ast-boiler-core
Version: 1.0.1
Summary: core for flask
Home-page: UNKNOWN
Author: Alex Astafev
Author-email: efsneiron@gmail.com
License: UNKNOWN
Keywords: boiler,core,flask
Platform: UNKNOWN
Requires-Python: >=3.6
Provides-Extra: test
